[
    {
        "function": "minecraft:set_written_book_pages",
        "mode": "append",
        "pages": [
            [
                {"text":"   ","font":"uniform"},
                {"text":"Repeat × Minecart\n\n","underlined":true,"bold":true},
                "   Combining the essence of production with treasure generates random item stacks from any loot table. Every four cycles of the item giver a single item stack is generated from any loot table."
            ]
        ],
        "conditions": [
            {
                "condition": "minecraft:value_check",
                "value": {
                    "type": "minecraft:score",
                    "target": {"type": "minecraft:fixed","name": "command/repeat_minecart"},
                    "score": "ris.alchemy_item_settings"
                },
                "range": 1
            },
            {
                "condition": "minecraft:entity_properties",
                "entity": "this",
                "predicate": {
                    "type_specific": {
                        "type": "minecraft:player",
                        "advancements": {
                            "ris:alchemy/transmutation/true_alchemist": {
                                "command/repeat_minecart": true
                            }
                        }
                    }
                }
            }
        ]
    },
    {
        "function": "minecraft:set_written_book_pages",
        "mode": "append",
        "pages": [
            [
                {"text":"   ","font":"uniform"},
                {"text":"Repeat × Minecart\n\n","underlined":true,"bold":true},
                {"text":" <This feature is disabled>","italic":true}
            ]
        ],
        "conditions": [
            {
                "condition": "minecraft:value_check",
                "value": {
                    "type": "minecraft:score",
                    "target": {"type": "minecraft:fixed","name": "command/repeat_minecart"},
                    "score": "ris.alchemy_item_settings"
                },
                "range": 0
            }
        ]
    }
]