{
    "pools": [
        {
            "rolls": 1,
            "entries": [
                {
                    "type": "minecraft:alternatives",
                    "children": [
                        {
                            "type": "minecraft:group",
                            "children": [
                                {
                                    "type": "minecraft:tag",
                                    "name": "ris:all_items",
                                    "weight": 1,
                                    "expand": true
                                },
                                {
                                    "type": "minecraft:loot_table",
                                    "value": "ris:custom_items/op",
                                    "weight": 24
                                },
                                {
                                    "type": "minecraft:loot_table",
                                    "value": "ris:custom_items/other",
                                    "weight": 16
                                }
                            ],
                            "conditions": [
                                {
                                    "condition": "minecraft:reference",
                                    "name": "ris:creator_heads/roarkcats"
                                },
                                {
                                    "condition": "minecraft:inverted",
                                    "term": {
                                        "condition": "minecraft:value_check",
                                        "value": {
                                            "type": "minecraft:score",
                                            "target": {
                                                "type": "minecraft:fixed",
                                                "name": "creator_heads"
                                            },
                                            "score": "ris.special_item_settings"
                                        },
                                        "range": 0
                                    }
                                }
                            ]
                        },
                        {
                            "type": "minecraft:group",
                            "children": [
                                {
                                    "type": "minecraft:tag",
                                    "name": "ris:all_items",
                                    "weight": 1,
                                    "expand": true
                                },
                                {
                                    "type": "minecraft:loot_table",
                                    "value": "ris:custom_items/all",
                                    "weight": 24
                                }
                            ]
                        }
                    ]
                }
            ],
            "functions": [
                {
                    "function": "minecraft:set_count",
                    "count": 2,
                    "conditions": [
                        {
                            "condition": "minecraft:reference",
                            "name": "ris:creator_heads/ziplaw"
                        },
                        {
                            "condition": "minecraft:inverted",
                            "term": {
                                "condition": "minecraft:value_check",
                                "value": {
                                    "type": "minecraft:score",
                                    "target": {
                                        "type": "minecraft:fixed",
                                        "name": "creator_heads"
                                    },
                                    "score": "ris.special_item_settings"
                                },
                                "range": 0
                            }
                        }
                    ]
                },
                {
                    "function": "minecraft:filtered",
                    "item_filter": {
                        "items": "#minecraft:shulker_boxes"
                    },
                    "modifier": {
                        "function": "minecraft:set_loot_table",
                        "type": "minecraft:shulker_box",
                        "name": "ris:loot_box"
                    },
                    "conditions": [
                        {
                            "condition": "minecraft:value_check",
                            "value": {
                                "type": "minecraft:score",
                                "target": {
                                    "type": "minecraft:fixed",
                                    "name": "loot_box_shulkers"
                                },
                                "score": "ris.settings"
                            },
                            "range": 1
                        },
                        {
                            "condition": "minecraft:entity_properties",
                            "entity": "this",
                            "predicate": {
                                "type": "minecraft:player"
                            }
                        }
                    ]
                }
            ]
        }
    ]
}