{
    "display": {
        "icon": {
            "id": "minecraft:feather"
        },
        "title": "An Endless Abyss",
        "description": "Fall into the void",
        "frame": "task"
    },
    "parent": "ris:ris/root",
    "criteria": {
        "requirement": {
            "trigger": "minecraft:entity_hurt_player",
            "conditions": {
                "player": [
                    {
                        "condition": "minecraft:reference",
                        "name": "ris:y_range_void"
                    }
                ],
                "damage": {
                    "type": {
						"tags": [
							{
								"id": "minecraft:bypasses_invulnerability",
								"expected": true
							}
						]
                    }
                }
            }
        }
    }
}