{
    "display": {
        "icon": {
            "id": "minecraft:music_disc_11"
        },
        "title": "Broken Record",
        "description": "Find and play all Music Discs",
        "frame": "challenge"
    },
    "parent": "ris:ris/groovin",
    "criteria": {
        "disc_13": {
            "trigger": "minecraft:item_used_on_block",
            "conditions": {
                "location": [
                    {
                        "condition": "minecraft:match_tool",
                        "predicate": {
                            "items": "minecraft:music_disc_13"
                        }
                    },
                    {
                        "condition": "minecraft:location_check",
                        "predicate": {
                            "block": {
                                "blocks": [
                                    "minecraft:jukebox"
                                ]
                            }
                        }
                    }
                ]
            }
        },
        "disc_cat": {
            "trigger": "minecraft:item_used_on_block",
            "conditions": {
                "location": [
                    {
                        "condition": "minecraft:match_tool",
                        "predicate": {
                            "items": "minecraft:music_disc_cat"
                        }
                    },
                    {
                        "condition": "minecraft:location_check",
                        "predicate": {
                            "block": {
                                "blocks": [
                                    "minecraft:jukebox"
                                ]
                            }
                        }
                    }
                ]
            }
        },
        "disc_blocks": {
            "trigger": "minecraft:item_used_on_block",
            "conditions": {
                "location": [
                    {
                        "condition": "minecraft:match_tool",
                        "predicate": {
                            "items": "minecraft:music_disc_blocks"
                        }
                    },
                    {
                        "condition": "minecraft:location_check",
                        "predicate": {
                            "block": {
                                "blocks": [
                                    "minecraft:jukebox"
                                ]
                            }
                        }
                    }
                ]
            }
        },
        "disc_chirp": {
            "trigger": "minecraft:item_used_on_block",
            "conditions": {
                "location": [
                    {
                        "condition": "minecraft:match_tool",
                        "predicate": {
                            "items": "minecraft:music_disc_chirp"
                        }
                    },
                    {
                        "condition": "minecraft:location_check",
                        "predicate": {
                            "block": {
                                "blocks": [
                                    "minecraft:jukebox"
                                ]
                            }
                        }
                    }
                ]
            }
        },
        "disc_far": {
            "trigger": "minecraft:item_used_on_block",
            "conditions": {
                "location": [
                    {
                        "condition": "minecraft:match_tool",
                        "predicate": {
                            "items": "minecraft:music_disc_far"
                        }
                    },
                    {
                        "condition": "minecraft:location_check",
                        "predicate": {
                            "block": {
                                "blocks": [
                                    "minecraft:jukebox"
                                ]
                            }
                        }
                    }
                ]
            }
        },
        "disc_mall": {
            "trigger": "minecraft:item_used_on_block",
            "conditions": {
                "location": [
                    {
                        "condition": "minecraft:match_tool",
                        "predicate": {
                            "items": "minecraft:music_disc_mall"
                        }
                    },
                    {
                        "condition": "minecraft:location_check",
                        "predicate": {
                            "block": {
                                "blocks": [
                                    "minecraft:jukebox"
                                ]
                            }
                        }
                    }
                ]
            }
        },
        "disc_mellohi": {
            "trigger": "minecraft:item_used_on_block",
            "conditions": {
                "location": [
                    {
                        "condition": "minecraft:match_tool",
                        "predicate": {
                            "items": "minecraft:music_disc_mellohi"
                        }
                    },
                    {
                        "condition": "minecraft:location_check",
                        "predicate": {
                            "block": {
                                "blocks": [
                                    "minecraft:jukebox"
                                ]
                            }
                        }
                    }
                ]
            }
        },
        "disc_stal": {
            "trigger": "minecraft:item_used_on_block",
            "conditions": {
                "location": [
                    {
                        "condition": "minecraft:match_tool",
                        "predicate": {
                            "items": "minecraft:music_disc_stal"
                        }
                    },
                    {
                        "condition": "minecraft:location_check",
                        "predicate": {
                            "block": {
                                "blocks": [
                                    "minecraft:jukebox"
                                ]
                            }
                        }
                    }
                ]
            }
        },
        "disc_strad": {
            "trigger": "minecraft:item_used_on_block",
            "conditions": {
                "location": [
                    {
                        "condition": "minecraft:match_tool",
                        "predicate": {
                            "items": "minecraft:music_disc_strad"
                        }
                    },
                    {
                        "condition": "minecraft:location_check",
                        "predicate": {
                            "block": {
                                "blocks": [
                                    "minecraft:jukebox"
                                ]
                            }
                        }
                    }
                ]
            }
        },
        "disc_ward": {
            "trigger": "minecraft:item_used_on_block",
            "conditions": {
                "location": [
                    {
                        "condition": "minecraft:match_tool",
                        "predicate": {
                            "items": "minecraft:music_disc_ward"
                        }
                    },
                    {
                        "condition": "minecraft:location_check",
                        "predicate": {
                            "block": {
                                "blocks": [
                                    "minecraft:jukebox"
                                ]
                            }
                        }
                    }
                ]
            }
        },
        "disc_11": {
            "trigger": "minecraft:item_used_on_block",
            "conditions": {
                "location": [
                    {
                        "condition": "minecraft:match_tool",
                        "predicate": {
                            "items": "minecraft:music_disc_11"
                        }
                    },
                    {
                        "condition": "minecraft:location_check",
                        "predicate": {
                            "block": {
                                "blocks": [
                                    "minecraft:jukebox"
                                ]
                            }
                        }
                    }
                ]
            }
        },
        "disc_wait": {
            "trigger": "minecraft:item_used_on_block",
            "conditions": {
                "location": [
                    {
                        "condition": "minecraft:match_tool",
                        "predicate": {
                            "items": "minecraft:music_disc_wait"
                        }
                    },
                    {
                        "condition": "minecraft:location_check",
                        "predicate": {
                            "block": {
                                "blocks": [
                                    "minecraft:jukebox"
                                ]
                            }
                        }
                    }
                ]
            }
        },
        "disc_pigstep": {
            "trigger": "minecraft:item_used_on_block",
            "conditions": {
                "location": [
                    {
                        "condition": "minecraft:match_tool",
                        "predicate": {
                            "items": "minecraft:music_disc_pigstep"
                        }
                    },
                    {
                        "condition": "minecraft:location_check",
                        "predicate": {
                            "block": {
                                "blocks": [
                                    "minecraft:jukebox"
                                ]
                            }
                        }
                    }
                ]
            }
        },
        "disc_otherside": {
            "trigger": "minecraft:item_used_on_block",
            "conditions": {
                "location": [
                    {
                        "condition": "minecraft:match_tool",
                        "predicate": {
                            "items": "minecraft:music_disc_otherside"
                        }
                    },
                    {
                        "condition": "minecraft:location_check",
                        "predicate": {
                            "block": {
                                "blocks": [
                                    "minecraft:jukebox"
                                ]
                            }
                        }
                    }
                ]
            }
        },
        "disc_5": {
            "trigger": "minecraft:item_used_on_block",
            "conditions": {
                "location": [
                    {
                        "condition": "minecraft:match_tool",
                        "predicate": {
                            "items": "minecraft:music_disc_5"
                        }
                    },
                    {
                        "condition": "minecraft:location_check",
                        "predicate": {
                            "block": {
                                "blocks": [
                                    "minecraft:jukebox"
                                ]
                            }
                        }
                    }
                ]
            }
        },
        "music_disc_relic": {
            "trigger": "minecraft:item_used_on_block",
            "conditions": {
                "location": [
                    {
                        "condition": "minecraft:match_tool",
                        "predicate": {
                            "items": "minecraft:music_disc_relic"
                        }
                    },
                    {
                        "condition": "minecraft:location_check",
                        "predicate": {
                            "block": {
                                "blocks": [
                                    "minecraft:jukebox"
                                ]
                            }
                        }
                    }
                ]
            }
        },
        "music_disc_creator": {
            "trigger": "minecraft:item_used_on_block",
            "conditions": {
                "location": [
                    {
                        "condition": "minecraft:match_tool",
                        "predicate": {
                            "items": "minecraft:music_disc_creator"
                        }
                    },
                    {
                        "condition": "minecraft:location_check",
                        "predicate": {
                            "block": {
                                "blocks": [
                                    "minecraft:jukebox"
                                ]
                            }
                        }
                    }
                ]
            }
        },
        "music_disc_creator_music_box": {
            "trigger": "minecraft:item_used_on_block",
            "conditions": {
                "location": [
                    {
                        "condition": "minecraft:match_tool",
                        "predicate": {
                            "items": "minecraft:music_disc_creator_music_box"
                        }
                    },
                    {
                        "condition": "minecraft:location_check",
                        "predicate": {
                            "block": {
                                "blocks": [
                                    "minecraft:jukebox"
                                ]
                            }
                        }
                    }
                ]
            }
        },
        "music_disc_precipice": {
            "trigger": "minecraft:item_used_on_block",
            "conditions": {
                "location": [
                    {
                        "condition": "minecraft:match_tool",
                        "predicate": {
                            "items": "minecraft:music_disc_precipice"
                        }
                    },
                    {
                        "condition": "minecraft:location_check",
                        "predicate": {
                            "block": {
                                "blocks": [
                                    "minecraft:jukebox"
                                ]
                            }
                        }
                    }
                ]
            }
        }
    }
}